hacs_frontend/__init__.py
hacs_frontend/entrypoint.js
hacs_frontend/extra.js
hacs_frontend/version.py
hacs_frontend/frontend_es5/1009.aOgS8TITRsI.js
hacs_frontend/frontend_es5/1009.aOgS8TITRsI.js.gz
hacs_frontend/frontend_es5/1009.aOgS8TITRsI.js.map
hacs_frontend/frontend_es5/1049.xMQc0QudPQE.js
hacs_frontend/frontend_es5/1049.xMQc0QudPQE.js.gz
hacs_frontend/frontend_es5/1049.xMQc0QudPQE.js.map
hacs_frontend/frontend_es5/1064._Oj9KHqBMEk.js
hacs_frontend/frontend_es5/1064._Oj9KHqBMEk.js.gz
hacs_frontend/frontend_es5/1064._Oj9KHqBMEk.js.map
hacs_frontend/frontend_es5/1117.tJSySHITJZE.js
hacs_frontend/frontend_es5/1117.tJSySHITJZE.js.gz
hacs_frontend/frontend_es5/1117.tJSySHITJZE.js.map
hacs_frontend/frontend_es5/1189.9tm4F5Jw27Q.js
hacs_frontend/frontend_es5/1189.9tm4F5Jw27Q.js.LICENSE.txt
hacs_frontend/frontend_es5/1189.9tm4F5Jw27Q.js.gz
hacs_frontend/frontend_es5/1189.9tm4F5Jw27Q.js.map
hacs_frontend/frontend_es5/1195.E-6gA55jDx8.js
hacs_frontend/frontend_es5/1195.E-6gA55jDx8.js.gz
hacs_frontend/frontend_es5/1195.E-6gA55jDx8.js.map
hacs_frontend/frontend_es5/1244.zJBQ8QvnNhs.js
hacs_frontend/frontend_es5/1244.zJBQ8QvnNhs.js.gz
hacs_frontend/frontend_es5/1244.zJBQ8QvnNhs.js.map
hacs_frontend/frontend_es5/1303.IExF4a4KLPU.js
hacs_frontend/frontend_es5/1303.IExF4a4KLPU.js.gz
hacs_frontend/frontend_es5/1303.IExF4a4KLPU.js.map
hacs_frontend/frontend_es5/1318.5_cxq66QzzY.js
hacs_frontend/frontend_es5/1318.5_cxq66QzzY.js.gz
hacs_frontend/frontend_es5/1318.5_cxq66QzzY.js.map
hacs_frontend/frontend_es5/1336.Fy4Hytu44Hc.js
hacs_frontend/frontend_es5/1336.Fy4Hytu44Hc.js.gz
hacs_frontend/frontend_es5/1336.Fy4Hytu44Hc.js.map
hacs_frontend/frontend_es5/141.w_RBtFv_90o.js
hacs_frontend/frontend_es5/141.w_RBtFv_90o.js.LICENSE.txt
hacs_frontend/frontend_es5/141.w_RBtFv_90o.js.gz
hacs_frontend/frontend_es5/141.w_RBtFv_90o.js.map
hacs_frontend/frontend_es5/1457.P08NbxN5Y1c.js
hacs_frontend/frontend_es5/1457.P08NbxN5Y1c.js.LICENSE.txt
hacs_frontend/frontend_es5/1457.P08NbxN5Y1c.js.gz
hacs_frontend-20240119163101.dist-info/LICENSE
hacs_frontend-20240119163101.dist-info/METADATA
hacs_frontend-20240119163101.dist-info/WHEEL
hacs_frontend-20240119163101.dist-info/top_level.txt
hacs_frontend-20240119163101.dist-info/RECORD
