Metadata-Version: 2.1
Name: hacs-frontend
Version: 20240119163101
Summary: The HACS frontend
Home-page: https://github.com/hacs/frontend
Author: Joakim Sorensen
Author-email: ludeeus@gmail.com
License-File: LICENSE
